scheduletools/__init__.py
scheduletools/_version.py
scheduletools/cli.py
scheduletools/core.py
scheduletools/exceptions.py
scheduletools/__pycache__/__init__.cpython-312.pyc
scheduletools/__pycache__/__init__.cpython-313.pyc
scheduletools/__pycache__/cli.cpython-313.pyc
scheduletools/__pycache__/core.cpython-312.pyc
scheduletools/__pycache__/core.cpython-313.pyc
scheduletools/__pycache__/exceptions.cpython-312.pyc
scheduletools/__pycache__/exceptions.cpython-313.pyc
scheduletools-0.4.0.dist-info/licenses/LICENSE
scheduletools-0.4.0.dist-info/METADATA
scheduletools-0.4.0.dist-info/WHEEL
scheduletools-0.4.0.dist-info/entry_points.txt
scheduletools-0.4.0.dist-info/top_level.txt
scheduletools-0.4.0.dist-info/RECORD
