Metadata-Version: 2.4
Name: scheduletools
Version: 0.4.0
Summary: Professional spreadsheet wrangling utilities for parsing, splitting, and expanding schedule data.
Author-email: "Khris Griffis, Ph.D." <khris.griffis.phd@gmail.com>
License: MIT
Project-URL: Homepage, https://github.com/Khlick/scheduletools
Project-URL: Repository, https://github.com/Khlick/scheduletools
Project-URL: Documentation, https://github.com/Khlick/scheduletools/blob/main/README.md
Project-URL: Issues, https://github.com/Khlick/scheduletools/issues
Classifier: Development Status :: 4 - Beta
Classifier: Intended Audience :: Developers
Classifier: License :: OSI Approved :: MIT License
Classifier: Operating System :: OS Independent
Classifier: Programming Language :: Python :: 3
Classifier: Programming Language :: Python :: 3.12
Classifier: Programming Language :: Python :: 3.13
Classifier: Topic :: Software Development :: Libraries :: Python Modules
Classifier: Topic :: Text Processing :: Filters
Classifier: Topic :: Utilities
Requires-Python: >=3.12
License-File: LICENSE
Requires-Dist: pandas>=2.0
Requires-Dist: click>=8.0
Provides-Extra: dev
Requires-Dist: pytest>=7.0; extra == "dev"
Requires-Dist: pytest-cov>=4.0; extra == "dev"
Requires-Dist: black>=23.0; extra == "dev"
Requires-Dist: flake8>=6.0; extra == "dev"
Requires-Dist: mypy>=1.0; extra == "dev"
Dynamic: license-file
